README.md
setup.py
PyQuantumE/__init__.py
PyQuantumE/constant.py
PyQuantumE.egg-info/PKG-INFO
PyQuantumE.egg-info/SOURCES.txt
PyQuantumE.egg-info/dependency_links.txt
PyQuantumE.egg-info/not-zip-safe
PyQuantumE.egg-info/requires.txt
PyQuantumE.egg-info/top_level.txt