Metadata-Version: 2.1
Name: PyQuantumE
Version: 0.0.1
Summary: PyQuantumE(Quantum Expresso)
Home-page: https://gitee.com/alkemie_gjwang/PyQuantumE
Author: Guanjie Wang
Author-email: gjwang@buaa.edu.cn
License: MIT
Platform: UNKNOWN
